SystemDelays.v
`define MEM_RWB_DELAY 1
`define MEM_OP_DELAY 1
`define AU_OP_DELAY 1
`define EDGE_DELAY 1

SystemArchHeader.v
`define DATA_WIDTH 16
`define OPCODE_WIDTH 4
`define REG_ADDR_WIDTH 4
`define MEM_WORD_WIDTH 16
`define MEM_ADDR_WIDTH 8

`define OPCODE_OFFSET `DATA_WIDTH
`define REG_DEST_OFFSET `OPCODE_OFFSET - `OPCODE_WIDTH
`define REG_SRC1_OFFSET `REG_DEST_OFFSET - `REG_ADDR_WIDTH 
`define REG_SRC2_OFFSET `REG_SRC1_OFFSET - `REG_ADDR_WIDTH 
`define CONST_OFFSET `REG_ADDR_WIDTH + `REG_SRC2_OFFSET

InstructionSetHeader.v
`include "SystemArchHeader.v"

`define NOP `OPCODE_WIDTH'h0
`define HLT `OPCODE_WIDTH'h1
`define LDPC `OPCODE_WIDTH'h2
`define MV `OPCODE_WIDTH'h3
`define LD `OPCODE_WIDTH'h4
`define LDI `OPCODE_WIDTH'h5
`define ST `OPCODE_WIDTH'h6
`define STI `OPCODE_WIDTH'h7
`define ADD `OPCODE_WIDTH'h8
`define ADDI `OPCODE_WIDTH'h9
`define SUB `OPCODE_WIDTH'hA
`define SUBI `OPCODE_WIDTH'hB
`define MULT `OPCODE_WIDTH'hC
`define MULTI `OPCODE_WIDTH'hD
`define DIV `OPCODE_WIDTH'hE
`define DIVI `OPCODE_WIDTH'hF

AU.v
`include "InstructionSetHeader.v"
`include "SystemArchHeader.v"

module AU(
		input wire Global_clk,
		input wire AU_op_enable,
		input wire [`OPCODE_WIDTH-1:0] Mode,
		input wire [`DATA_WIDTH-1:0] AU_in_1,
		input wire [`DATA_WIDTH-1:0] AU_in_2,
		output reg [`DATA_WIDTH-1:0] AU_out
	);
	
	reg output_signbit;
	reg [`DATA_WIDTH-1:0] tmp_in_1, tmp_in_2, tmp_swap;

	always @(posedge AU_op_enable) begin
		tmp_in_1 = AU_in_1;
		tmp_in_1[`MSB] = 0;
		tmp_in_2 = AU_in_2;
		tmp_in_2[`MSB] = 0;
		if (Mode == `MULT | Mode == `DIV) begin
			output_signbit = AU_in_1[`MSB] ^ AU_in_2[`MSB];
		end else begin
			 if (tmp_in_1 > tmp_in_2) begin
			 	output_signbit = AU_in_1[`MSB];
			 end else begin
			 	if (Mode == `SUB) begin
			 		output_signbit = ~AU_in_2[`MSB];	
			 	end else begin
			 		output_signbit = AU_in_2[`MSB];
			 	end
			 	tmp_swap = tmp_in_1;
			 	tmp_in_1 = tmp_in_2;
			 	tmp_in_2 = tmp_swap;	
			 end
		end


		case (Mode)	
			`NOP:	begin
						$display("Stall");
					end
			`ADD:	begin
						$display("Adding in AU");
						if (AU_in_1[`MSB] ^ AU_in_2[`MSB]) begin
							AU_out = tmp_in_1 - tmp_in_2;
							AU_out[`MSB] = output_signbit;	
						end else begin
							AU_out = tmp_in_1 + tmp_in_2;
							AU_out[`MSB] = output_signbit;
						end
						
						$display("%d + %d = %d", AU_in_1, AU_in_2, AU_out);
					end

			`SUB:	begin
						$display("Substracting in AU");
						if (AU_in_1[`MSB] ^ AU_in_2[`MSB]) begin
							AU_out = tmp_in_1 + tmp_in_2;
							AU_out[`MSB] = output_signbit;	
						end else begin
							AU_out = tmp_in_1 - tmp_in_2;
							AU_out[`MSB] = output_signbit;
						end
						$display("%d - %d = %d", AU_in_1, AU_in_2, AU_out);
					end

			`MULT:	begin
						$display("Multiplying in AU");
						AU_out = AU_in_1 * AU_in_2;
						AU_out[`MSB] = output_signbit;
						$display("%d * %d = %d", AU_in_1, AU_in_2, AU_out);
					end

			`DIV:	begin
						$display("Dividing in AU");
						AU_out = AU_in_1 / AU_in_2;	
						AU_out[`MSB] = output_signbit;
						$display("%d / %d = %d", AU_in_1, AU_in_2, AU_out);
					end
		endcase
		//AU_out[`MSB] = output_signbit;							
	end
endmodule

/*
module AU_tb;
	reg [`DATA_WIDTH-1:0] A, B;
	wire [`DATA_WIDTH-1:0] Y;
	reg [`OPCODE_WIDTH-1:0] Mode;
	AU test_au(Mode, A, B, Y);

	initial begin
		#1	A = `DATA_WIDTH'h3;
			B = `DATA_WIDTH'h2;
			Mode = `ADD;
		
		$finish;
	end
endmodule
*/

MEMU.v
`include "SystemArchHeader.v"
`include "SystemDelays.v"

module MEMU(
		input wire Global_clk,
		input wire Read_back_sig,
		input wire Write_back_sig,
		input wire Read_sig,
		input wire Write_sig,
		input wire Mem_op_enable,
		input wire[`MEM_ADDR_WIDTH-1:0] Address_in,
		input wire[`MEM_WORD_WIDTH-1:0] Data_in,
		output reg[`MEM_WORD_WIDTH-1:0] Data_out
	);
	reg [`MEM_WORD_WIDTH-1:0] mem [0:2**`MEM_ADDR_WIDTH-1];
	integer i, file;

	always @(posedge Read_back_sig) begin
		file = $fopen("test_rom.mem", "r");
		$display ("test_rom.mem opened for readback");
		if (file == 0) begin
    		$display ("ERROR: test_rom.mem not opened");
		end else begin
			$readmemh("test_rom.mem", mem);
			//$display("%d -> %x%x%x%x", 15, mem[15][3:0], mem[15][7:4], mem[15][11:8], mem[15][15:12]);
			$display ("Successfully read back");
			$fclose(file);
		end
	end

	always @(posedge Write_back_sig) begin
		file = $fopen("test_rom.mem", "w");
		$display ("test_rom.mem opened for wirteback");
		if (file == 0) begin
    		$display ("ERROR: test_rom.mem not opened");
		end else begin
			for(i = 0; i < 2**`MEM_ADDR_WIDTH; i+=1) begin
				$fdisplay(file, "%x%x%x%x", mem[i][15:12], mem[i][11:8], mem[i][7:4], mem[i][3:0]);
			end
			$display ("Successfully written back");
			$fclose(file);
		end
	end

	always @(posedge Mem_op_enable) begin
		if (Read_sig & !Write_sig) begin
			Data_out = mem[Address_in];
			$display("Reading from Memloc %d, Data %x%x%x%x", Address_in, Data_out[15:12], Data_out[11:8], Data_out[7:4], Data_out[3:0]);
		end
		else if (Write_sig & !Read_sig) begin
			mem[Address_in] = Data_in;
			$display("Writing to Memloc %d, Data %x%x%x%x", Address_in, mem[Address_in][15:12], mem[Address_in][11:8], mem[Address_in][7:4], mem[Address_in][3:0]);
		end
		else begin
			$display("Stall");
		end
	end
endmodule

/*
module MEMU_tb();
	reg Write_back_sig, Read_back_sig, Read_sig, Write_sig, Mem_op_enable;
	reg [`MEM_ADDR_WIDTH-1:0] Address_in;
	reg [`MEM_WORD_WIDTH-1:0] Data_in;
	wire [`MEM_WORD_WIDTH-1:0] Data_out;
	wire Mem_op_success;
	MEMU test_memu(Read_back_sig, Write_back_sig, Read_sig, Write_sig, Mem_op_enable, Address_in, Data_in, Data_out, Mem_op_success);

	initial begin
			Read_back_sig = 1;
			Read_back_sig = 0;
		#1	Read_sig = 1;
			Write_sig = 0;
			Address_in = `MEM_ADDR_WIDTH'h0F;
			Mem_op_enable = 1;
			Mem_op_enable = 0;
		
		#1	Read_sig = 0;
			Write_sig = 1;
			Address_in = `MEM_ADDR_WIDTH'h0F;
			Data_in = `MEM_WORD_WIDTH'hF00F;
			Mem_op_enable = 1;
			Mem_op_enable = 0;	
		#1
			Write_back_sig = 1;
			Write_back_sig = 0;
		#1
		$finish;
	end
endmodule
*/

EXEU.v
`include "InstructionSetHeader.v"
`include "SystemArchHeader.v"
`include "SystemDelays.v"

module EXEU();
	integer i, total_clk_cycle;
	reg Global_clk, hlt;
	reg [`MEM_WORD_WIDTH-1:0] reg_bank [0:2**`REG_ADDR_WIDTH-1];
	reg [`MEM_ADDR_WIDTH-1:0] PC;
	reg [`OPCODE_WIDTH-1:0] Opcode;
	reg [`REG_ADDR_WIDTH-1:0] Dest_reg, Src_reg1, Src_reg2;
	reg [`MEM_ADDR_WIDTH-1:0] Dest_address;

	reg Write_back_sig, Read_back_sig, Read_sig, Write_sig, Mem_op_enable;
	reg [`MEM_ADDR_WIDTH-1:0] MAR;
	reg [`MEM_WORD_WIDTH-1:0] MDR_out;
	wire [`MEM_WORD_WIDTH-1:0] MDR_in;
	MEMU test_memu(Global_clk, Read_back_sig, Write_back_sig, Read_sig, Write_sig, Mem_op_enable, MAR, MDR_out, MDR_in);

	reg AU_op_enable;
	reg [`DATA_WIDTH-1:0] AU_in1, AU_in2;
	wire [`DATA_WIDTH-1:0] AU_out;
	reg [`OPCODE_WIDTH-1:0] Mode;
	AU test_au(Global_clk, AU_op_enable, Mode, AU_in1, AU_in2, AU_out);

	always begin
		#1 Global_clk = ~Global_clk;
		total_clk_cycle += 1;
	end

	initial begin
		$dumpfile("my_dumpfile.vcd");
		$dumpvars;
		//Reset Global_clk
		total_clk_cycle = 0;
		Global_clk = 0;
		//Start processor
		hlt = 0;
		//Load RAM from file
		Read_back_sig = 1;
		Read_back_sig = 0;
		repeat (`MEM_RWB_DELAY) begin
			@ (posedge Global_clk);
		end		
		//Load PC with starting address
		PC = `MEM_ADDR_WIDTH'h00;
		//hlt = 0;
		while (!hlt) begin	
			//IF
			Read_sig = 1;
			Write_sig = 0;
			MAR = PC;
			Mem_op_enable = 1;
			repeat (`EDGE_DELAY) begin
				@ (posedge Global_clk);
			end					
			Mem_op_enable = 0;
			repeat (`MEM_OP_DELAY) begin
				@ (posedge Global_clk);
			end
			Read_sig = 0;
			$display("Executing Insruction %x%x%x%x", MDR_in[15:12], MDR_in[11:8], MDR_in[7:4], MDR_in[3:0]);
			Opcode = MDR_in[`OPCODE_OFFSET-1:`OPCODE_OFFSET-`OPCODE_WIDTH];
			
			//ID
			if (Opcode[`OPCODE_WIDTH-1]) begin   		//AU operations	
				if(Opcode[0]) begin 					//Immediate addressing mode operations- ADDI, SUBI, MULTI, DIVI
					Dest_reg = MDR_in[`REG_DEST_OFFSET-1: `REG_DEST_OFFSET - `REG_ADDR_WIDTH];
					Src_reg1 = MDR_in[`REG_SRC1_OFFSET-1:`REG_SRC2_OFFSET];
					$display("Loading Immediate");
					PC += 1;
					Read_sig = 1;
					Write_sig = 0;
					MAR = PC;
					Mem_op_enable = 1;
					repeat (`EDGE_DELAY) begin
						@ (posedge Global_clk);
					end
					Mem_op_enable = 0;
					repeat (`MEM_OP_DELAY) begin
						@ (posedge Global_clk);
					end
					Read_sig = 0;
					AU_in1 = reg_bank[Src_reg1];
					AU_in2 = MDR_in;
					Mode = Opcode;
					Mode[0] = 0;
					AU_op_enable = 1;
					repeat (`EDGE_DELAY) begin
						@ (posedge Global_clk);
					end		
					AU_op_enable = 0;
					repeat (`AU_OP_DELAY) begin
						@ (posedge Global_clk);
					end
					reg_bank[Dest_reg] = AU_out;
					for(i = 0; i < 2**`REG_ADDR_WIDTH; i+=1) begin
						$display("Reg[%x] = %x%x%x%x", i, reg_bank[i][15:12], reg_bank[i][11:8], reg_bank[i][7:4], reg_bank[i][3:0]);
					end
				end else begin 							//Register addressing mode operations- ADD, SUB, MULT, DIV
					Dest_reg = MDR_in[`REG_DEST_OFFSET-1:`REG_DEST_OFFSET-`REG_ADDR_WIDTH];
					Src_reg1 = MDR_in[`REG_SRC1_OFFSET-1:`REG_SRC2_OFFSET];
					Src_reg2 = MDR_in[`REG_SRC2_OFFSET-1:`REG_SRC2_OFFSET-`REG_ADDR_WIDTH];
					AU_in1 = reg_bank[Src_reg1];
					AU_in2 = reg_bank[Src_reg2];
					Mode = Opcode;
					AU_op_enable = 1;
					repeat (`EDGE_DELAY) begin
						@ (posedge Global_clk);
					end		
					AU_op_enable = 0;
					repeat (`AU_OP_DELAY) begin
						@ (posedge Global_clk);
					end
					reg_bank[Dest_reg] = AU_out;
					for(i = 0; i < 2**`REG_ADDR_WIDTH; i+=1) begin
						$display("Reg[%x] = %x%x%x%x", i, reg_bank[i][15:12], reg_bank[i][11:8], reg_bank[i][7:4], reg_bank[i][3:0]);
					end
				end 
			end else begin  		//MEM Operations	
				case (Opcode)
					`NOP:	begin
								$display("Stalling");
							end
					`HLT:	begin
								$display("Halting");
								hlt = 1;
							end
					`MV:	begin
								Dest_reg = MDR_in[`REG_DEST_OFFSET-1:`REG_DEST_OFFSET-`REG_ADDR_WIDTH];
								Src_reg1 = MDR_in[`REG_SRC1_OFFSET-1:`REG_SRC2_OFFSET];
								$display("Moving from reg %d to reg %d", Src_reg1, Dest_reg);
								reg_bank[Dest_reg] = reg_bank[Src_reg1];
								for(i = 0; i < 2**`REG_ADDR_WIDTH; i+=1) begin
									$display("Reg[%x] = %x%x%x%x", i, reg_bank[i][15:12], reg_bank[i][11:8], reg_bank[i][7:4], reg_bank[i][3:0]);
								end
							end
					
					`LD:	begin
								$display("Loading");
								Dest_reg = MDR_in[`REG_DEST_OFFSET-1:`REG_DEST_OFFSET-`REG_ADDR_WIDTH];
								MAR = MDR_in[`REG_SRC1_OFFSET-1:`REG_SRC1_OFFSET-`MEM_ADDR_WIDTH];
								Read_sig = 1;
								Write_sig = 0;
								Mem_op_enable = 1;
								repeat (`EDGE_DELAY) begin
									@ (posedge Global_clk);
								end
								Mem_op_enable = 0;
								repeat (`MEM_OP_DELAY) begin
									@ (posedge Global_clk);
								end
								Read_sig = 0;
								reg_bank[Dest_reg] = MDR_in;
								for(i = 0; i < 2**`REG_ADDR_WIDTH; i+=1) begin
									$display("Reg[%x] = %x%x%x%x", i, reg_bank[i][15:12], reg_bank[i][11:8], reg_bank[i][7:4], reg_bank[i][3:0]);
								end
							end
					
					`LDI:	begin
								$display("Loading Immediate");
								Dest_reg = MDR_in[`REG_DEST_OFFSET-1:`REG_DEST_OFFSET-`REG_ADDR_WIDTH];
								PC += 1;
								Read_sig = 1;
								Write_sig = 0;
								MAR = PC;
								Mem_op_enable = 1;
								repeat (`EDGE_DELAY) begin
									@ (posedge Global_clk);
								end
								Mem_op_enable = 0;
								repeat (`MEM_OP_DELAY) begin
									@ (posedge Global_clk);
								end
								Read_sig = 0;
								reg_bank[Dest_reg] = MDR_in;
								for(i = 0; i < 2**`REG_ADDR_WIDTH; i+=1) begin
									$display("Reg[%x] = %x%x%x%x", i, reg_bank[i][15:12], reg_bank[i][11:8], reg_bank[i][7:4], reg_bank[i][3:0]);
								end	
							end
					`ST:	begin
								$display("Storing");
								Dest_reg = MDR_in[`REG_DEST_OFFSET-1:`REG_DEST_OFFSET-`REG_ADDR_WIDTH];
								MAR = MDR_in[`REG_SRC1_OFFSET-1:`REG_SRC1_OFFSET-`MEM_ADDR_WIDTH];
								MDR_out = reg_bank[Dest_reg];
								Read_sig = 0;
								Write_sig = 1;
								Mem_op_enable = 1;
								repeat (`EDGE_DELAY) begin
									@ (posedge Global_clk);
								end
								Mem_op_enable = 0;
								repeat (`MEM_OP_DELAY) begin
									@ (posedge Global_clk);
								end
								Write_sig = 0;
							end	
					`STI:	begin
								$display("Storing Immediate");
								Dest_address = MDR_in[`REG_SRC1_OFFSET-1:0];
								PC += 1;
								MAR = PC;
								Read_sig = 1;
								Write_sig = 0;
								Mem_op_enable = 1;
								repeat (`EDGE_DELAY) begin
									@ (posedge Global_clk);
								end
								Mem_op_enable = 0;
								repeat (`MEM_OP_DELAY) begin
									@ (posedge Global_clk);
								end
								Read_sig = 0;
								MAR = Dest_address;
								MDR_out = MDR_in;
								Read_sig = 0;
								Write_sig = 1;
								Mem_op_enable = 1;
								repeat (`EDGE_DELAY) begin
									@ (posedge Global_clk);
								end
								Mem_op_enable = 0;
								repeat (`MEM_OP_DELAY) begin
									@ (posedge Global_clk);
								end
								Write_sig = 0; 
							end
				endcase
			end
		PC += 1;	
		end
		//Write RAM back to file
		Write_back_sig = 1;
		Write_back_sig = 0;
		repeat (`MEM_RWB_DELAY) begin
			@ (posedge Global_clk);
		end
		$display("Number of clock cycle = %d", total_clk_cycle);
		$finish;			
	end	
endmodule

my_dumpfile.vcd
$date
	Tue May 08 14:27:33 2018
$end
$version
	Icarus Verilog
$end
$timescale
	1s
$end
$scope module EXEU $end
$var wire 16 ! MDR_in [15:0] $end
$var wire 16 " AU_out [15:0] $end
$var reg 16 # AU_in1 [15:0] $end
$var reg 16 $ AU_in2 [15:0] $end
$var reg 1 % AU_op_enable $end
$var reg 8 & Dest_address [7:0] $end
$var reg 4 ' Dest_reg [3:0] $end
$var reg 1 ( Global_clk $end
$var reg 8 ) MAR [7:0] $end
$var reg 16 * MDR_out [15:0] $end
$var reg 1 + Mem_op_enable $end
$var reg 4 , Mode [3:0] $end
$var reg 4 - Opcode [3:0] $end
$var reg 8 . PC [7:0] $end
$var reg 1 / Read_back_sig $end
$var reg 1 0 Read_sig $end
$var reg 4 1 Src_reg1 [3:0] $end
$var reg 4 2 Src_reg2 [3:0] $end
$var reg 1 3 Write_back_sig $end
$var reg 1 4 Write_sig $end
$var reg 1 5 hlt $end
$var integer 32 6 i [31:0] $end
$var integer 32 7 total_clk_cycle [31:0] $end
$scope module test_au $end
$var wire 16 8 AU_in_1 [15:0] $end
$var wire 16 9 AU_in_2 [15:0] $end
$var wire 1 % AU_op_enable $end
$var wire 1 ( Global_clk $end
$var wire 4 : Mode [3:0] $end
$var reg 16 ; AU_out [15:0] $end
$var reg 1 < output_signbit $end
$var reg 16 = tmp_in_1 [15:0] $end
$var reg 16 > tmp_in_2 [15:0] $end
$var reg 16 ? tmp_swap [15:0] $end
$upscope $end
$scope module test_memu $end
$var wire 8 @ Address_in [7:0] $end
$var wire 16 A Data_in [15:0] $end
$var wire 1 ( Global_clk $end
$var wire 1 + Mem_op_enable $end
$var wire 1 / Read_back_sig $end
$var wire 1 0 Read_sig $end
$var wire 1 3 Write_back_sig $end
$var wire 1 4 Write_sig $end
$var reg 16 B Data_out [15:0] $end
$var integer 32 C file [31:0] $end
$var integer 32 D i [31:0] $end
$upscope $end
$upscope $end
$enddefinitions $end
#0
$dumpvars
bx D
b10000000000000000000000000000011 C
bx B
bx A
bx @
bx ?
bx >
bx =
x<
bx ;
bx :
bx 9
bx 8
b0 7
bx 6
05
x4
x3
bx 2
bx 1
x0
0/
bx .
bx -
bx ,
x+
bx *
bx )
0(
bx '
bx &
x%
bx $
bx #
bx "
bx !
$end
#1
b111xxxx10000000 !
b111xxxx10000000 B
1+
b0 )
b0 @
04
10
b0 .
b1 7
1(
#2
b10 7
0(
#3
0+
b11 7
1(
#4
b100 7
0(
#5
b1100100 !
b1100100 B
1+
b1 )
b1 @
b1 .
b10000000 &
b111 -
10
b101 7
1(
#6
b110 7
0(
#7
0+
b111 7
1(
#8
b1000 7
0(
#9
1+
14
b1100100 *
b1100100 A
b10000000 )
b10000000 @
00
b1001 7
1(
#10
b1010 7
0(
#11
0+
b1011 7
1(
#12
b1100 7
0(
#13
b1010000xxxxxxxx !
b1010000xxxxxxxx B
1+
b10 )
b10 @
10
b10 .
04
b1101 7
1(
#14
b1110 7
0(
#15
0+
b1111 7
1(
#16
b10000 7
0(
#17
b0 !
b0 B
1+
b11 )
b11 @
b11 .
b0 '
b101 -
10
b10001 7
1(
#18
b10010 7
0(
#19
0+
b10011 7
1(
#20
b10100 7
0(
#21
b101100000000xxxx !
b101100000000xxxx B
1+
b100 )
b100 @
b100 .
b10000 6
10
b10101 7
1(
#22
b10110 7
0(
#23
0+
b10111 7
1(
#24
b11000 7
0(
#25
b101 !
b101 B
1+
b101 )
b101 @
b101 .
b0 1
b1011 -
10
b11001 7
1(
#26
b11010 7
0(
#27
0+
b11011 7
1(
#28
b11100 7
0(
#29
b1000000000000101 "
b1000000000000101 ;
b0 ?
1<
b0 >
b101 =
1%
b1010 ,
b1010 :
b101 $
b101 9
b0 #
b0 8
00
b11101 7
1(
#30
b11110 7
0(
#31
0%
b11111 7
1(
#32
b100000 7
0(
#33
b100000110000000 !
b100000110000000 B
1+
b110 )
b110 @
10
b110 .
b10000 6
b100001 7
1(
#34
b100010 7
0(
#35
0+
b100011 7
1(
#36
b100100 7
0(
#37
b1100100 !
b1100100 B
1+
b10000000 )
b10000000 @
b1 '
b100 -
10
b100101 7
1(
#38
b100110 7
0(
#39
0+
b100111 7
1(
#40
b101000 7
0(
#41
b101100010001xxxx !
b101100010001xxxx B
1+
b111 )
b111 @
b111 .
b10000 6
10
b101001 7
1(
#42
b101010 7
0(
#43
0+
b101011 7
1(
#44
b101100 7
0(
#45
b1010 !
b1010 B
1+
b1000 )
b1000 @
b1000 .
b1 1
b1011 -
10
b101101 7
1(
#46
b101110 7
0(
#47
0+
b101111 7
1(
#48
b110000 7
0(
#49
b1011010 "
b1011010 ;
0<
b1010 >
b1100100 =
1%
b1010 ,
b1010 :
b1010 $
b1010 9
b1100100 #
b1100100 8
00
b110001 7
1(
#50
b110010 7
0(
#51
0%
b110011 7
1(
#52
b110100 7
0(
#53
b110100100001xxxx !
b110100100001xxxx B
1+
b1001 )
b1001 @
10
b1001 .
b10000 6
b110101 7
1(
#54
b110110 7
0(
#55
0+
b110111 7
1(
#56
b111000 7
0(
#57
b100 !
b100 B
1+
b1010 )
b1010 @
b1010 .
b10 '
b1101 -
10
b111001 7
1(
#58
b111010 7
0(
#59
0+
b111011 7
1(
#60
b111100 7
0(
#61
b101101000 "
b101101000 ;
b100 >
b1011010 =
1%
b1100 ,
b1100 :
b100 $
b100 9
b1011010 #
b1011010 8
00
b111101 7
1(
#62
b111110 7
0(
#63
0%
b111111 7
1(
#64
b1000000 7
0(
#65
b1000000100000010 !
b1000000100000010 B
1+
b1011 )
b1011 @
10
b1011 .
b10000 6
b1000001 7
1(
#66
b1000010 7
0(
#67
0+
b1000011 7
1(
#68
b1000100 7
0(
#69
b101100011 "
b101100011 ;
b101 ?
b101 >
b101101000 =
1%
b1000 ,
b1000 :
b101101000 $
b101101000 9
b1000000000000101 #
b1000000000000101 8
b10 2
b0 1
b1 '
b1000 -
00
b1000101 7
1(
#70
b1000110 7
0(
#71
0%
b1000111 7
1(
#72
b1001000 7
0(
#73
b110000110000001 !
b110000110000001 B
1+
b1100 )
b1100 @
10
b1100 .
b10000 6
b1001001 7
1(
#74
b1001010 7
0(
#75
0+
b1001011 7
1(
#76
b1001100 7
0(
#77
1+
14
b101100011 *
b101100011 A
b10000001 )
b10000001 @
b110 -
00
b1001101 7
1(
#78
b1001110 7
0(
#79
0+
b1001111 7
1(
#80
b1010000 7
0(
#81
b1xxxxxxxxxxxx !
b1xxxxxxxxxxxx B
1+
b1101 )
b1101 @
10
b1101 .
04
b1010001 7
1(
#82
b1010010 7
0(
#83
0+
b1010011 7
1(
#84
b1010100 7
0(
#85
b100000000 D
03
b1110 .
15
b1 -
00
b1010101 7
1(
#86
b1010110 7
0(
#87
b1010111 7
1(
